lovely/__init__.py
lovely/love.py
lovepackage-0.1.dist-info/METADATA
lovepackage-0.1.dist-info/WHEEL
lovepackage-0.1.dist-info/top_level.txt
lovepackage-0.1.dist-info/RECORD
