Metadata-Version: 2.4
Name: lovepackage
Version: 0.1
Summary: A lovely message from Harshith to Mushaib
Author: Harshith
Requires-Python: >=3.6
Dynamic: author
Dynamic: requires-python
Dynamic: summary
